LICENSE
MANIFEST.in
README.md
setup.cfg
setup.py
DoCodeCarga/__init__.py
DoCodeCarga/admin.py
DoCodeCarga/apps.py
DoCodeCarga/models.py
DoCodeCarga/urls.py
DoCodeCarga/views.py
DoCodeCarga/migrations/__init__.py
DoCodeCarga/migrations/__pycache__/__init__.cpython-37.pyc
DoCodeCarga/procesos/layout.py
DoCodeCarga/procesos/procesos.py
DoCodeCarga/procesos/__pycache__/layout.cpython-37.pyc
DoCodeCarga/procesos/__pycache__/procesos.cpython-37.pyc
DoCodeCarga/static/js/demo.js
DoCodeCarga/templates/layoutCarga.html
DoCodeCarga/templatetags/filtroCarga.py
DoCodeCarga/templatetags/__pycache__/filtroCarga.cpython-37.pyc
DoCodeCarga/templatetags/__pycache__/filtros.cpython-37.pyc
dj_DoCodeCarga.egg-info/PKG-INFO
dj_DoCodeCarga.egg-info/SOURCES.txt
dj_DoCodeCarga.egg-info/dependency_links.txt
dj_DoCodeCarga.egg-info/top_level.txt