Metadata-Version: 2.1
Name: dj-DoCodeCarga
Version: 1.0.4
Summary: Manage DataBase Models Easy.
Home-page: https://github.com/DoCodeSoft/DoCodeCarga
Author: DoCode
Author-email: aurea@docode.com.mx,mario@docode.com.mx,elias@docode.com.mx
License: MIT
Platform: UNKNOWN
Classifier: Environment :: Web Environment
Classifier: Framework :: Django
Classifier: Intended Audience :: Developers
Classifier: License :: OSI Approved :: BSD License
Classifier: Operating System :: OS Independent
Classifier: Programming Language :: Python
Classifier: Topic :: Internet :: WWW/HTTP
